alimits/__init__.py
alimits/storage/__init__.py
alimits/storage/base.py
alimits/storage/memory.py
alimits/storage/redis.py
alimits/strategies.py
alimits-1.0.0.dist-info/LICENSE
alimits-1.0.0.dist-info/WHEEL
alimits-1.0.0.dist-info/METADATA
alimits-1.0.0.dist-info/RECORD
