Metadata-Version: 2.1
Name: alimits
Version: 1.0.0
Summary: Provides asyncio storage and strategy implementations for the limits library.
Home-page: https://github.com/thearchitector/alimits
License: MIT
Keywords: limits,rate limiting,api,asyncio,fastapi,aiohttp
Author: Elias Gabriel
Author-email: me@eliasfgabriel.com
Requires-Python: >=3.7,<4.0
Classifier: License :: OSI Approved :: MIT License
Classifier: Programming Language :: Python :: 3
Classifier: Programming Language :: Python :: 3.7
Classifier: Programming Language :: Python :: 3.8
Classifier: Programming Language :: Python :: 3.9
Requires-Dist: limits (>=1.5.1,<2.0.0)
Project-URL: Documentation, https://thearchitector.github.io/alimits
Project-URL: Repository, https://github.com/thearchitector/alimits
